aiosteam/__init__.py
aiosteam/main.py
aiosteam/process.py
aiosteam/struct.py
aiosteam-0.0.2a0.dist-info/METADATA
aiosteam-0.0.2a0.dist-info/WHEEL
aiosteam-0.0.2a0.dist-info/top_level.txt
aiosteam-0.0.2a0.dist-info/RECORD
